aeroutils/__init__.py
aeroutils/version.py
aeroutils-22.4.dist-info/LICENSE
aeroutils-22.4.dist-info/METADATA
aeroutils-22.4.dist-info/WHEEL
aeroutils-22.4.dist-info/top_level.txt
aeroutils-22.4.dist-info/RECORD
