Metadata-Version: 2.1
Name: aeroutils
Version: 22.4
Summary: Importable utilities for aerospace problem solving.
Home-page: https://github.com/MattCJones/aeroutils
Author: Matthew C. Jones
Author-email: matt.c.jones.aoe@gmail.com
License: MIT License
Keywords: utility aerospace engineering design problem solving
Platform: UNKNOWN
Classifier: Development Status :: 4 - Beta
Classifier: Intended Audience :: Science/Research
Classifier: License :: OSI Approved :: MIT License
Classifier: Natural Language :: English
Classifier: Operating System :: OS Independent
Classifier: Topic :: Scientific/Engineering
Classifier: Topic :: Utilities
Classifier: Programming Language :: Python :: 3.8
Classifier: Programming Language :: Python :: 3.9
Requires-Python: >=3.8
License-File: LICENSE
Requires-Dist: pint
Requires-Dist: numpy
